picross_solver/__init__.py
picross_solver/picross_solver.py
picross_solver-1.1.2.dist-info/LICENSE
picross_solver-1.1.2.dist-info/METADATA
picross_solver-1.1.2.dist-info/WHEEL
picross_solver-1.1.2.dist-info/top_level.txt
picross_solver-1.1.2.dist-info/RECORD
