Metadata-Version: 2.1
Name: picross-solver
Version: 1.1.2
Summary: A picross/nonogram solver.
Home-page: https://github.com/swifteralex/picross-solver
Author: Alexander Coats
Author-email: swifteralexc@gmail.com
License: UNKNOWN
Platform: UNKNOWN
Classifier: Programming Language :: Python :: 3
Classifier: License :: OSI Approved :: MIT License
Classifier: Operating System :: OS Independent
Requires-Python: >=3.4
License-File: LICENSE
